Workbook
Name Slicer_Category: #N/A
Name Slicer_Category1: #N/A
Name Slicer_City: #N/A
Name Slicer_City1: #N/A
Name Slicer_Inventory_Status: #N/A
Name Slicer_Outlet: #N/A
Name Slicer_Outlet1: #N/A
Name Slicer_Payment_Mode: #N/A
Name Slicer_Payment_Mode1: #N/A
Name Slicer_Product: #N/A

Sheet tblBlinkit
A1: Order_ID | B1: Order_Date | C1: Day_Type | D1: City | E1: Outlet | F1: Category | G1: Product | H1: Quantity | I1: Unit_Price | J1: Discount_% | K1: Sales_Amount | L1: Customer_Rating | M1: Payment_Mode | N1: Inventory_Available | O1: Reorder_Level | P1: Month | Q1: Month_Name | R1: Year | S1: Sales_lakh | T1: Order_Count | U1: Inventory_Status
A2: ORD1002 | B2: 2025-01-23 | C2: =IF(WEEKDAY(Table1[[#This Row],[Order_Date]],2)<=5,"Weekday","Weekend") -> Weekday | D2: Mumbai | E2: Outlet C | F2: Beverages | G2: Soft Drink | H2: 3 | I2: 106.3 | J2: 15 | K2: 271.06 | L2: 3.9 | M2: Net Banking | N2: 33 | O2: 24 | P2: =DATE(YEAR(Table1[[#This Row],[Order_Date]]),MONTH(Table1[[#This Row],[Order_Date]]),1) -> 45658 | Q2: =TEXT(Table1[[#This Row],[Order_Date]],"mmmmmmmm") -> January | R2: =YEAR(Table1[[#This Row],[Order_Date]]) -> 2025 | S2: =Table1[[#This Row],[Sales_Amount]]/100000 -> 0.0027106 | T2: =1 -> 1 | U2: =IF(Table1[[#This Row],[Inventory_Available]]<=Table1[[#This Row],[Reorder_Level]],"Reorder Required","Sufficient") -> Sufficient
A3: ORD1003 | B3: 2025-03-30 | C3: =IF(WEEKDAY(Table1[[#This Row],[Order_Date]],2)<=5,"Weekday","Weekend") -> Weekend | D3: Delhi | E3: Outlet C | F3: Personal Care | G3: Toothpaste | H3: 8 | I3: 202.07 | J3: 5 | K3: 1535.73 | L3: 4 | M3: Net Banking | N3: 307 | O3: 32 | P3: =DATE(YEAR(Table1[[#This Row],[Order_Date]]),MONTH(Table1[[#This Row],[Order_Date]]),1) -> 45717 | Q3: =TEXT(Table1[[#This Row],[Order_Date]],"mmmmmmmm") -> March | R3: =YEAR(Table1[[#This Row],[Order_Date]]) -> 2025 | S3: =Table1[[#This Row],[Sales_Amount]]/100000 -> 0.0153573 | T3: =1 -> 1 | U3: =IF(Table1[[#This Row],[Inventory_Available]]<=Table1[[#This Row],[Reorder_Level]],"Reorder Required","Sufficient") -> Sufficient
A4: ORD1004 | B4: 2025-03-21 | C4: =IF(WEEKDAY(Table1[[#This Row],[Order_Date]],2)<=5,"Weekday","Weekend") -> Weekday | D4: Mumbai | E4: Outlet A | F4: Personal Care | G4: Face Wash | H4: 1 | I4: 417.15 | J4: 15 | K4: 354.58 | L4: 4.2 | M4: Card | N4: 149 | O4: 47 | P4: =DATE(YEAR(Table1[[#This Row],[Order_Date]]),MONTH(Table1[[#This Row],[Order_Date]]),1) -> 45717 | Q4: =TEXT(Table1[[#This Row],[Order_Date]],"mmmmmmmm") -> March | R4: =YEAR(Table1[[#This Row],[Order_Date]]) -> 2025 | S4: =Table1[[#This Row],[Sales_Amount]]/100000 -> 0.0035458 | T4: =1 -> 1 | U4: =IF(Table1[[#This Row],[Inventory_Available]]<=Table1[[#This Row],[Reorder_Level]],"Reorder Required","Sufficient") -> Sufficient
A5: ORD1005 | B5: 2025-04-22 | C5: =IF(WEEKDAY(Table1[[#This Row],[Order_Date]],2)<=5,"Weekday","Weekend") -> Weekday | D5: Pune | E5: Outlet A | F5: Personal Care | G5: Soap | H5: 9 | I5: 255.9 | J5: 20 | K5: 1842.48 | L5: 4.1 | M5: Card | N5: 84 | O5: 73 | P5: =DATE(YEAR(Table1[[#This Row],[Order_Date]]),MONTH(Table1[[#This Row],[Order_Date]]),1) -> 45748 | Q5: =TEXT(Table1[[#This Row],[Order_Date]],"mmmmmmmm") -> April | R5: =YEAR(Table1[[#This Row],[Order_Date]]) -> 2025 | S5: =Table1[[#This Row],[Sales_Amount]]/100000 -> 0.0184248 | T5: =1 -> 1 | U5: =IF(Table1[[#This Row],[Inventory_Available]]<=Table1[[#This Row],[Reorder_Level]],"Reorder Required","Sufficient") -> Sufficient
A6: ORD1006 | B6: 2025-02-16 | C6: =IF(WEEKDAY(Table1[[#This Row],[Order_Date]],2)<=5,"Weekday","Weekend") -> Weekend | D6: Bengaluru | E6: Outlet C | F6: Beverages | G6: Coffee | H6: 1 | I6: 85.18 | J6: 5 | K6: 80.92 | L6: 4.3 | M6: UPI | N6: 133 | O6: 48 | P6: =DATE(YEAR(Table1[[#This Row],[Order_Date]]),MONTH(Table1[[#This Row],[Order_Date]]),1) -> 45689 | Q6: =TEXT(Table1[[#This Row],[Order_Date]],"mmmmmmmm") -> February | R6: =YEAR(Table1[[#This Row],[Order_Date]]) -> 2025 | S6: =Table1[[#This Row],[Sales_Amount]]/100000 -> 0.0008092 | T6: =1 -> 1 | U6: =IF(Table1[[#This Row],[Inventory_Available]]<=Table1[[#This Row],[Reorder_Level]],"Reorder Required","Sufficient") -> Sufficient
A7: ORD1007 | B7: 2025-01-04 | C7: =IF(WEEKDAY(Table1[[#This Row],[Order_Date]],2)<=5,"Weekday","Weekend") -> Weekend | D7: Mumbai | E7: Outlet C | F7: Personal Care | G7: Shampoo | H7: 9 | I7: 215.86 | J7: 5 | K7: 1845.6 | L7: 4.2 | M7: Cash | N7: 23 | O7: 56 | P7: =DATE(YEAR(Table1[[#This Row],[Order_Date]]),MONTH(Table1[[#This Row],[Order_Date]]),1) -> 45658 | Q7: =TEXT(Table1[[#This Row],[Order_Date]],"mmmmmmmm") -> January | R7: =YEAR(Table1[[#This Row],[Order_Date]]) -> 2025 | S7: =Table1[[#This Row],[Sales_Amount]]/100000 -> 0.018456 | T7: =1 -> 1 | U7: =IF(Table1[[#This Row],[Inventory_Available]]<=Table1[[#This Row],[Reorder_Level]],"Reorder Required","Sufficient") -> Reorder Required
A8: ORD1008 | B8: 2025-03-25 | C8: =IF(WEEKDAY(Table1[[#This Row],[Order_Date]],2)<=5,"Weekday","Weekend") -> Weekday | D8: Chennai | E8: Outlet A | F8: Personal Care | G8: Soap | H8: 6 | I8: 295.4 | J8: 5 | K8: 1683.78 | L8: 4.1 | M8: Card | N8: 10 | O8: 24 | P8: =DATE(YEAR(Table1[[#This Row],[Order_Date]]),MONTH(Table1[[#This Row],[Order_Date]]),1) -> 45717 | Q8: =TEXT(Table1[[#This Row],[Order_Date]],"mmmmmmmm") -> March | R8: =YEAR(Table1[[#This Row],[Order_Date]]) -> 2025 | S8: =Table1[[#This Row],[Sales_Amount]]/100000 -> 0.0168378 | T8: =1 -> 1 | U8: =IF(Table1[[#This Row],[Inventory_Available]]<=Table1[[#This Row],[Reorder_Level]],"Reorder Required","Sufficient") -> Reorder Required
A9: ORD1009 | B9: 2025-02-17 | C9: =IF(WEEKDAY(Table1[[#This Row],[Order_Date]],2)<=5,"Weekday","Weekend") -> Weekday | D9: Delhi | E9: Outlet C | F9: Snacks | G9: Namkeen | H9: 2 | I9: 426.35 | J9: 0 | K9: 852.7 | L9: 4.5 | M9: Cash | N9: 139 | O9: 29 | P9: =DATE(YEAR(Table1[[#This Row],[Order_Date]]),MONTH(Table1[[#This Row],[Order_Date]]),1) -> 45689 | Q9: =TEXT(Table1[[#This Row],[Order_Date]],"mmmmmmmm") -> February | R9: =YEAR(Table1[[#This Row],[Order_Date]]) -> 2025 | S9: =Table1[[#This Row],[Sales_Amount]]/100000 -> 0.008527 | T9: =1 -> 1 | U9: =IF(Table1[[#This Row],[Inventory_Available]]<=Table1[[#This Row],[Reorder_Level]],"Reorder Required","Sufficient") -> Sufficient
A10: ORD1010 | B10: 2025-03-03 | C10: =IF(WEEKDAY(Table1[[#This Row],[Order_Date]],2)<=5,"Weekday","Weekend") -> Weekday | D10: Bengaluru | E10: Outlet B | F10: Beverages | G10: Soft Drink | H10: 7 | I10: 59.03 | J10: 0 | K10: 413.21 | L10: 3.8 | M10: Cash | N10: 208 | O10: 46 | P10: =DATE(YEAR(Table1[[#This Row],[Order_Date]]),MONTH(Table1[[#This Row],[Order_Date]]),1) -> 45717 | Q10: =TEXT(Table1[[#This Row],[Order_Date]],"mmmmmmmm") -> March | R10: =YEAR(Table1[[#This Row],[Order_Date]]) -> 2025 | S10: =Table1[[#This Row],[Sales_Amount]]/100000 -> 0.0041321 | T10: =1 -> 1 | U10: =IF(Table1[[#This Row],[Inventory_Available]]<=Table1[[#This Row],[Reorder_Level]],"Reorder Required","Sufficient") -> Sufficient
A11: ORD1011 | B11: 2025-04-13 | C11: =IF(WEEKDAY(Table1[[#This Row],[Order_Date]],2)<=5,"Weekday","Weekend") -> Weekend | D11: Mumbai | E11: Outlet A | F11: Snacks | G11: Cookies | H11: 6 | I11: 308.4 | J11: 0 | K11: 1850.4 | L11: 4.4 | M11: Card | N11: 387 | O11: 38 | P11: =DATE(YEAR(Table1[[#This Row],[Order_Date]]),MONTH(Table1[[#This Row],[Order_Date]]),1) -> 45748 | Q11: =TEXT(Table1[[#This Row],[Order_Date]],"mmmmmmmm") -> April | R11: =YEAR(Table1[[#This Row],[Order_Date]]) -> 2025 | S11: =Table1[[#This Row],[Sales_Amount]]/100000 -> 0.018504 | T11: =1 -> 1 | U11: =IF(Table1[[#This Row],[Inventory_Available]]<=Table1[[#This Row],[Reorder_Level]],"Reorder Required","Sufficient") -> Sufficient
A12: ORD1012 | B12: 2025-01-18 | C12: =IF(WEEKDAY(Table1[[#This Row],[Order_Date]],2)<=5,"Weekday","Weekend") -> Weekend | D12: Chennai | E12: Outlet B | F12: Personal Care | G12: Shampoo | H12: 1 | I12: 329.07 | J12: 5 | K12: 312.62 | L12: 4 | M12: Cash | N12: 494 | O12: 24 | P12: =DATE(YEAR(Table1[[#This Row],[Order_Date]]),MONTH(Table1[[#This Row],[Order_Date]]),1) -> 45658 | Q12: =TEXT(Table1[[#This Row],[Order_Date]],"mmmmmmmm") -> January | R12: =YEAR(Table1[[#This Row],[Order_Date]]) -> 2025 | S12: =Table1[[#This Row],[Sales_Amount]]/100000 -> 0.0031262 | T12: =1 -> 1 | U12: =IF(Table1[[#This Row],[Inventory_Available]]<=Table1[[#This Row],[Reorder_Level]],"Reorder Required","Sufficient") -> Sufficient
A13: ORD1013 | B13: 2025-05-07 | C13: =IF(WEEKDAY(Table1[[#This Row],[Order_Date]],2)<=5,"Weekday","Weekend") -> Weekday | D13: Bengaluru | E13: Outlet D | F13: Fruits | G13: Mango | H13: 7 | I13: 305.07 | J13: 15 | K13: 1815.17 | L13: 3.8 | M13: UPI | N13: 408 | O13: 52 | P13: =DATE(YEAR(Table1[[#This Row],[Order_Date]]),MONTH(Table1[[#This Row],[Order_Date]]),1) -> 45778 | Q13: =TEXT(Table1[[#This Row],[Order_Date]],"mmmmmmmm") -> May | R13: =YEAR(Table1[[#This Row],[Order_Date]]) -> 2025 | S13: =Table1[[#This Row],[Sales_Amount]]/100000 -> 0.0181517 | T13: =1 -> 1 | U13: =IF(Table1[[#This Row],[Inventory_Available]]<=Table1[[#This Row],[Reorder_Level]],"Reorder Required","Sufficient") -> Sufficient
... A501: ORD1501 | B501: 2025-06-25 | C501: =IF(WEEKDAY(Table1[[#This Row],[Order_Date]],2)<=5,"Weekday","Weekend") -> Weekday | D501: Delhi | E501: Outlet B | F501: Snacks | G501: Chips | H501: 5 | I501: 347.21 | J501: 20 | K501: 1388.84 | L501: 4.6 | M501: Cash | N501: 117 | O501: 35 | P501: =DATE(YEAR(Table1[[#This Row],[Order_Date]]),MONTH(Table1[[#This Row],[Order_Date]]),1) -> 45809 | Q501: =TEXT(Table1[[#This Row],[Order_Date]],"mmmmmmmm") -> June | R501: =YEAR(Table1[[#This Row],[Order_Date]]) -> 2025 | S501: =Table1[[#This Row],[Sales_Amount]]/100000 -> 0.0138884 | T501: =1 -> 1 | U501: =IF(Table1[[#This Row],[Inventory_Available]]<=Table1[[#This Row],[Reorder_Level]],"Reorder Required","Sufficient") -> Sufficient

Sheet Pivot 1
A3: Row Labels | B3: Sum of Sales_Amount
A4: Jan | B4: 89739.22
A5: Feb | B5: 94916.59
A6: Mar | B6: 99000.39
A7: Apr | B7: 116681.38
A8: May | B8: 123492.51
A9: Jun | B9: 107374.32
A10: Grand Total | B10: 631204.41

Sheet Pivot 2
A3: Row Labels | B3: Sum of Sales_Amount
A4: Beverages | B4: 121298.73
A5: Dairy | B5: 124729.19
A6: Fruits | B6: 167992.89
A7: Personal Care | B7: 109667.64
A8: Snacks | B8: 107515.96
A9: Grand Total | B9: 631204.41

Sheet Pivot 3
A3: Row Labels | B3: Sum of Sales_Amount
A4: Hyderabad | B4: 88029.93
A5: Pune | B5: 101813.12
A6: Mumbai | B6: 106356.86
A7: Delhi | B7: 106626.85
A8: Chennai | B8: 109517.85
A9: Bengaluru | B9: 118859.8
A10: Grand Total | B10: 631204.41

Sheet Pivot 4
A3: Row Labels | B3: Sum of Sales_Amount
A4: Milk | B4: 29778.94
A5: Chips | B5: 33503.29
A6: Coffee | B6: 34349.3
A7: Cookies | B7: 35593.78
A8: Mango | B8: 35646.8
A9: Tea | B9: 36649.56
A10: Banana | B10: 36783.48
A11: Cheese | B11: 42379.96
A12: Orange | B12: 46676
A13: Apple | B13: 48886.61
A14: Grand Total | B14: 380247.72

Sheet Pivot 5
A3: Row Labels | B3: Sum of Sales_Amount
A4: Card | B4: 190912.2
A5: Cash | B5: 142671.47
A6: Net Banking | B6: 148348.9
A7: UPI | B7: 149271.84
A8: Grand Total | B8: 631204.41

Sheet Pivot 6
A3: Sum of Sales_Amount | B3: Column Labels
A4: Row Labels | B4: Weekday | C4: Weekend | D4: Grand Total
A5: Jan | B5: 55342.82 | C5: 34396.4 | D5: 89739.22
A6: Feb | B6: 74902.61 | C6: 20013.98 | D6: 94916.59
A7: Mar | B7: 54038.17 | C7: 44962.22 | D7: 99000.39
A8: Apr | B8: 79677.96 | C8: 37003.42 | D8: 116681.38
A9: May | B9: 89913.83 | C9: 33578.68 | D9: 123492.51
A10: Jun | B10: 73308.51 | C10: 34065.81 | D10: 107374.32
A11: Grand Total | B11: 427183.9 | C11: 204020.51 | D11: 631204.41

Sheet Pivot 7
A3: Row Labels | B3: Count of Order_ID
A4: Reorder Required | B4: 35
A5: Sufficient | B5: 465
A6: Grand Total | B6: 500

Sheet Pivot 8
A3: Category | B3: Sum of Sales_lakh | C3: Sum of Sales_Amount
A4: Beverages | B4: 1.2129873 | C4: 0.19217028
A5: Dairy | B5: 1.2472919 | C5: 0.19760507
A6: Fruits | B6: 1.6799289 | C6: 0.26614657
A7: Personal Care | B7: 1.0966764 | C7: 0.17374346
A8: Snacks | B8: 1.0751596 | C8: 0.17033461
A9: Grand Total | B9: 6.3120441 | C9: 1

Sheet Pivot 9
A3: City | B3: Sales (in lakh) | C3: % of Total
A4: Bengaluru | B4: 1.188598 | C4: 0.18830635
A5: Chennai | B5: 1.0951785 | C5: 0.17350615
A6: Delhi | B6: 1.0662685 | C6: 0.16892602
A7: Hyderabad | B7: 0.8802993 | C7: 0.13946343
A8: Mumbai | B8: 1.0635686 | C8: 0.16849828
A9: Pune | B9: 1.0181312 | C9: 0.16129976
A10: Grand Total | B10: 6.3120441 | C10: 1

Sheet Pivot 10
A3: Outlet | B3: Sum of Sales_lakh
A4: Outlet A | B4: 1.6308404
A5: Outlet B | B5: 1.5458109
A6: Outlet C | B6: 1.6715963
A7: Outlet D | B7: 1.4637965
A8: Grand Total | B8: 6.3120441

Sheet Pivot 11
A3: Month | B3: Sales (in lakh) | C3: Orders
A4: Jan | B4: 0.8973922 | C4: 79
A5: Feb | B5: 0.9491659 | C5: 77
A6: Mar | B6: 0.9900039 | C6: 81
A7: Apr | B7: 1.1668138 | C7: 79
A8: May | B8: 1.2349251 | C8: 95
A9: Jun | B9: 1.0737432 | C9: 89
A10: Grand Total | B10: 6.3120441 | C10: 500

Sheet Dashboard
A2: FILTERS | D2: BLINKIT SALES & INVENTORY DASHBOARD
AH3: =SUM(tblBlinkit!K2:K501) -> 631204.41
AH4: =SUM(tblBlinkit!T2:T501) -> 500
AH5: =SUM(tblBlinkit!H2:H501) -> 2677
AH6: =SUM(tblBlinkit!K2:K501)/SUM(tblBlinkit!T2:T501) -> 1262.4088
AH7: =AVERAGE(tblBlinkit!L2:L501) -> 4.236
AH8: =COUNTIF(tblBlinkit!U2:U501,"Reorder Required") -> 35
D10: SALES TREND (MONTHLY) | L10: SALES BY CATEGORY | S10: SALES BY CITY
D22: TOP 10 BEST SELLING PRODUCTS (BY SALES) | L22: SALES BY PAYMENT MODE | S22: SALES TREND (WEEKDAY VS WEEKEND)
D37: CATEGORY WISE SALES | H37: CITY WISE SALES | L37: OUTLET WISE SALES | O37: MONTHLY SALES SUMMARY | S37: KEY INSIGHTS
D38: Category | E38: Sum of Sales_lakh | F38: Sum of Sales_Amount | H38: City | I38: Sales (in lakh) | J38: % of Total | L38: Outlet | M38: Sum of Sales_lakh | O38: Month | P38: Sales (in lakh) | Q38: Orders
D39: Beverages | E39: 1.2129873 | F39: 0.19217028 | H39: Bengaluru | I39: 1.188598 | J39: 0.18830635 | L39: Outlet A | M39: 1.6308404 | O39: Jan | P39: 0.8973922 | Q39: 79
D40: Dairy | E40: 1.2472919 | F40: 0.19760507 | H40: Chennai | I40: 1.0951785 | J40: 0.17350615 | L40: Outlet B | M40: 1.5458109 | O40: Feb | P40: 0.9491659 | Q40: 77
D41: Fruits | E41: 1.6799289 | F41: 0.26614657 | H41: Delhi | I41: 1.0662685 | J41: 0.16892602 | L41: Outlet C | M41: 1.6715963 | O41: Mar | P41: 0.9900039 | Q41: 81
D42: Personal Care | E42: 1.0966764 | F42: 0.17374346 | H42: Hyderabad | I42: 0.8802993 | J42: 0.13946343 | L42: Outlet D | M42: 1.4637965 | O42: Apr | P42: 1.1668138 | Q42: 79
D43: Snacks | E43: 1.0751596 | F43: 0.17033461 | H43: Mumbai | I43: 1.0635686 | J43: 0.16849828 | L43: Grand Total | M43: 6.3120441 | O43: May | P43: 1.2349251 | Q43: 95
D44: Grand Total | E44: 6.3120441 | F44: 1 | H44: Pune | I44: 1.0181312 | J44: 0.16129976 | O44: Jun | P44: 1.0737432 | Q44: 89
H45: Grand Total | I45: 6.3120441 | J45: 1 | O45: Grand Total | P45: 6.3120441 | Q45: 500

Sheet Pivot Reports Dashboards
A1: PIVOT REPORTS DASHBOARD
B8: CATEGORY WISE SALES | M8: CITY WISE SALES
B9: Row Labels | C9: Sum of Sales_Amount | M9: Row Labels | N9: Sum of Sales_Amount
B10: Beverages | C10: 121298.73 | M10: Bengaluru | N10: 118859.8
B11: Dairy | C11: 124729.19 | M11: Chennai | N11: 109517.85
B12: Fruits | C12: 167992.89 | M12: Delhi | N12: 106626.85
B13: Personal Care | C13: 109667.64 | M13: Mumbai | N13: 106356.86
B14: Snacks | C14: 107515.96 | M14: Pune | N14: 101813.12
B15: Grand Total | C15: 631204.41 | M15: Hyderabad | N15: 88029.93
M16: Grand Total | N16: 631204.41
B22: OUTLET WISE SALES | M22: SALES BY PAYMENT MODE
B23: Row Labels | C23: Sum of Sales_Amount | M23: Row Labels | N23: Sum of Sales_Amount
B24: Outlet A | C24: 163084.04 | M24: Card | N24: 190912.2
B25: Outlet B | C25: 154581.09 | M25: Cash | N25: 142671.47
B26: Outlet C | C26: 167159.63 | M26: Net Banking | N26: 148348.9
B27: Outlet D | C27: 146379.65 | M27: UPI | N27: 149271.84
B28: Grand Total | C28: 631204.41 | M28: Grand Total | N28: 631204.41
B36: SALES TREND (MONTHLY) | M36: TOP 10 BEST SELLING PRODUCTS (BY SALES)
B37: Row Labels | C37: Sum of Sales_Amount | M37: Row Labels | N37: Sum of Sales_Amount
B38: Jan | C38: 89739.22 | M38: Milk | N38: 29778.94
B39: Feb | C39: 94916.59 | M39: Chips | N39: 33503.29
B40: Mar | C40: 99000.39 | M40: Coffee | N40: 34349.3
B41: Apr | C41: 116681.38 | M41: Cookies | N41: 35593.78
B42: May | C42: 123492.51 | M42: Mango | N42: 35646.8
B43: Jun | C43: 107374.32 | M43: Tea | N43: 36649.56
B44: Grand Total | C44: 631204.41 | M44: Banana | N44: 36783.48
M45: Cheese | N45: 42379.96
M46: Orange | N46: 46676
M47: Apple | N47: 48886.61
M48: Grand Total | N48: 380247.72

Sheet Pivot - Category
A3: Row Labels | B3: Sum of Sales_Amount
A4: Beverages | B4: 121298.73
A5: Dairy | B5: 124729.19
A6: Fruits | B6: 167992.89
A7: Personal Care | B7: 109667.64
A8: Snacks | B8: 107515.96
A9: Grand Total | B9: 631204.41

Sheet Pivot - City
A3: Row Labels | B3: Sum of Sales_Amount
A4: Bengaluru | B4: 118859.8
A5: Chennai | B5: 109517.85
A6: Delhi | B6: 106626.85
A7: Mumbai | B7: 106356.86
A8: Pune | B8: 101813.12
A9: Hyderabad | B9: 88029.93
A10: Grand Total | B10: 631204.41

Sheet Pivot - Outlet
A3: Row Labels | B3: Sum of Sales_Amount
A4: Outlet D | B4: 146379.65
A5: Outlet B | B5: 154581.09
A6: Outlet A | B6: 163084.04
A7: Outlet C | B7: 167159.63
A8: Grand Total | B8: 631204.41
